{
    "carBadges": {
        "electric": ["elettric"],
        "hybrid": ["bev", "fcev", "hev", "erev"]
    },
    "carVersionFuelMap": {
        "senza piombo": "benzina",
        "senza piombo \"premium\"": "benzina"
    },
    "configuratorFilterFuel": {
        "gasoline": {
            "value": "senza piombo",
            "engines": null
        },
        "gasoil": {
            "value": "diesel",
            "engines": null
        },
        "electric": {
            "value": "elettric",
            "engines": null
        },
        "gpl": {
            "value": "gpl",
            "engines": null
        },
        "gasolineHybrid": {
            "value": "senza piombo",
            "engines": ["bev", "fcev", "hev", "erev"]
        },
        "gasoilHybrid": {
            "value": "diesel",
            "engines": ["bev", "fcev", "hev", "erev"]
        }
    },
    "configuratorFilterStyle": ["Green", "Berlina", "Citycar", "Familiare/Lavoro", "Sportiva", "Suv/Crossover"],
    "headerSearch": true,
    "horizonIndexScoreMax": 0.15,
    "horizonIndexScoreWeight": 10000,
    "horizonOffices": [
        {
            "name": "Sede Centrale Milano",
            "address": "Via Copernico 4, 20090 Trezzano Sul Naviglio"
        },
        {
            "name": "Sede Bergamo",
            "address": "Via per Grumello 43/A, 24127 Bergamo"
        },
        {
            "name": "Sede Padova",
            "address": "Viale della Navigazione Interna 71, 35129 Padova"
        },
        {
            "name": "Sede Torino",
            "address": "Corso Valdocco 19, 10122 Torino"
        },
        {
            "name": "Sede San Benedetto del Tronto",
            "address": "Via Pomezia 3, 63074 San Benedetto del Tronto"
        }
    ],
    "telephonePrefix": "+39"
}
